pdf_to_markdown_mcp/__init__.py
pdf_to_markdown_mcp/server.py
pdf_to_markdown_mcp-0.1.0.dist-info/METADATA
pdf_to_markdown_mcp-0.1.0.dist-info/WHEEL
pdf_to_markdown_mcp-0.1.0.dist-info/entry_points.txt
pdf_to_markdown_mcp-0.1.0.dist-info/RECORD
