Metadata-Version: 2.4
Name: pdf-to-markdown-mcp
Version: 0.1.0
Summary: PDF转Markdown MCP服务器 - Python版本
Requires-Python: >=3.11
Requires-Dist: markitdown[pdf]>=0.0.1a3
Requires-Dist: mcp>=1.0.0
